rivr_rest_peewee/__init__.py
rivr_rest_peewee/attributes.py
rivr_rest_peewee/resources.py
rivr_rest_peewee/tests/__init__.py
rivr_rest_peewee/tests/test_attributes.py
rivr_rest_peewee/tests/test_resource.py
rivr_rest_peewee-0.2.0.dist-info/DESCRIPTION.rst
rivr_rest_peewee-0.2.0.dist-info/METADATA
rivr_rest_peewee-0.2.0.dist-info/metadata.json
rivr_rest_peewee-0.2.0.dist-info/RECORD
rivr_rest_peewee-0.2.0.dist-info/top_level.txt
rivr_rest_peewee-0.2.0.dist-info/WHEEL
