Metadata-Version: 2.0
Name: rivr-rest-peewee
Version: 0.2.0
Summary: Library for building REST APIs with rivr and peewee.
Home-page: https://github.com/rivrproject/rivr-rest-peewee
Author: Kyle Fuller
Author-email: inbox@kylefuller.co.uk
License: BSD
Platform: UNKNOWN
Classifier: Programming Language :: Python :: 2
Classifier: Programming Language :: Python :: 2.7
Classifier: Programming Language :: Python :: 3
Classifier: Programming Language :: Python :: 3.2
Classifier: Programming Language :: Python :: 3.3
Classifier: Programming Language :: Python :: 3.4
Classifier: License :: OSI Approved :: BSD License
Requires-Dist: six
Requires-Dist: rivr-peewee
Requires-Dist: rivr-rest
